{
    "swagger": "2.0",
    "info": {
        "description": "This is the API documentation for Kredit Plus backend services.",
        "title": "BE Kredit Plus",
        "contact": {},
        "version": "1.0"
    },
    "basePath": "/",
    "paths": {
        "/v1/auth/login": {
            "post": {
                "description": "Handles user login by verifying credentials and returning authentication data.",
                "consumes": [
                    "application/json"
                ],
                "produces": [
                    "application/json"
                ],
                "tags": [
                    "auth"
                ],
                "summary": "Authenticate user login",
                "parameters": [
                    {
                        "description": "Payload",
                        "name": "request",
                        "in": "body",
                        "required": true,
                        "schema": {
                            "$ref": "#/definitions/model.LoginRequest"
                        }
                    }
                ],
                "responses": {
                    "200": {
                        "description": "Successful login response",
                        "schema": {
                            "$ref": "#/definitions/model.BaseResponse"
                        }
                    },
                    "401": {
                        "description": "Unauthorized error response",
                        "schema": {
                            "$ref": "#/definitions/model.BaseResponse"
                        }
                    }
                }
            }
        },
        "/v1/auth/me": {
            "get": {
                "security": [
                    {
                        "AccessToken": []
                    }
                ],
                "description": "Retrieves information about the currently authenticated user.",
                "consumes": [
                    "application/json"
                ],
                "produces": [
                    "application/json"
                ],
                "tags": [
                    "auth"
                ],
                "summary": "Get authenticated user info",
                "responses": {
                    "200": {
                        "description": "Successful user info response",
                        "schema": {
                            "allOf": [
                                {
                                    "$ref": "#/definitions/model.BaseResponse"
                                },
                                {
                                    "type": "object",
                                    "properties": {
                                        "data": {
                                            "$ref": "#/definitions/model.AuthMe"
                                        }
                                    }
                                }
                            ]
                        }
                    },
                    "401": {
                        "description": "Unauthorized error response",
                        "schema": {
                            "$ref": "#/definitions/model.BaseResponse"
                        }
                    }
                }
            }
        },
        "/v1/customer/information": {
            "get": {
                "security": [
                    {
                        "AccessToken": []
                    }
                ],
                "description": "Retrieves information about the customer.",
                "consumes": [
                    "application/json"
                ],
                "produces": [
                    "application/json"
                ],
                "tags": [
                    "customer"
                ],
                "summary": "Get customer information",
                "responses": {
                    "200": {
                        "description": "Successful customer information response",
                        "schema": {
                            "allOf": [
                                {
                                    "$ref": "#/definitions/model.BaseResponse"
                                },
                                {
                                    "type": "object",
                                    "properties": {
                                        "data": {
                                            "$ref": "#/definitions/model.CustomerResponse"
                                        }
                                    }
                                }
                            ]
                        }
                    },
                    "401": {
                        "description": "Unauthorized error response",
                        "schema": {
                            "$ref": "#/definitions/model.BaseResponse"
                        }
                    }
                }
            }
        },
        "/v1/customer/tenor": {
            "get": {
                "security": [
                    {
                        "AccessToken": []
                    }
                ],
                "description": "Retrieves available tenor for the customer.",
                "consumes": [
                    "application/json"
                ],
                "produces": [
                    "application/json"
                ],
                "tags": [
                    "customer"
                ],
                "summary": "Get customer tenor",
                "responses": {
                    "200": {
                        "description": "Successful customer tenor response",
                        "schema": {
                            "allOf": [
                                {
                                    "$ref": "#/definitions/model.BaseResponse"
                                },
                                {
                                    "type": "object",
                                    "properties": {
                                        "data": {
                                            "type": "array",
                                            "items": {
                                                "$ref": "#/definitions/model.TenorResponse"
                                            }
                                        }
                                    }
                                }
                            ]
                        }
                    },
                    "401": {
                        "description": "Unauthorized error response",
                        "schema": {
                            "$ref": "#/definitions/model.BaseResponse"
                        }
                    }
                }
            }
        },
        "/v1/loan": {
            "get": {
                "security": [
                    {
                        "AccessToken": []
                    }
                ],
                "description": "Retrieves available loans.",
                "consumes": [
                    "application/json"
                ],
                "produces": [
                    "application/json"
                ],
                "tags": [
                    "loan"
                ],
                "summary": "Get loan",
                "parameters": [
                    {
                        "type": "integer",
                        "default": 1,
                        "description": "Page",
                        "name": "page",
                        "in": "query"
                    },
                    {
                        "type": "integer",
                        "default": 10,
                        "description": "Per Page",
                        "name": "per_page",
                        "in": "query"
                    }
                ],
                "responses": {
                    "200": {
                        "description": "Successful loan list response",
                        "schema": {
                            "allOf": [
                                {
                                    "$ref": "#/definitions/model.BaseResponse"
                                },
                                {
                                    "type": "object",
                                    "properties": {
                                        "data": {
                                            "type": "array",
                                            "items": {
                                                "$ref": "#/definitions/model.LoanResponse"
                                            }
                                        }
                                    }
                                }
                            ]
                        }
                    },
                    "401": {
                        "description": "Unauthorized error response",
                        "schema": {
                            "$ref": "#/definitions/model.BaseResponse"
                        }
                    }
                }
            },
            "post": {
                "security": [
                    {
                        "AccessToken": []
                    }
                ],
                "description": "Creates a new loan.",
                "consumes": [
                    "application/json"
                ],
                "produces": [
                    "application/json"
                ],
                "tags": [
                    "loan"
                ],
                "summary": "Create loan",
                "parameters": [
                    {
                        "description": "Create Loan Request",
                        "name": "request",
                        "in": "body",
                        "required": true,
                        "schema": {
                            "$ref": "#/definitions/model.CreateLoanRequest"
                        }
                    }
                ],
                "responses": {
                    "201": {
                        "description": "Successful loan creation response",
                        "schema": {
                            "$ref": "#/definitions/model.BaseResponse"
                        }
                    },
                    "400": {
                        "description": "Bad request error response",
                        "schema": {
                            "$ref": "#/definitions/model.BaseResponse"
                        }
                    },
                    "401": {
                        "description": "Unauthorized error response",
                        "schema": {
                            "$ref": "#/definitions/model.BaseResponse"
                        }
                    },
                    "422": {
                        "description": "Validation error response",
                        "schema": {
                            "$ref": "#/definitions/model.BaseResponse"
                        }
                    }
                }
            }
        },
        "/v1/transaction": {
            "get": {
                "security": [
                    {
                        "AccessToken": []
                    }
                ],
                "description": "Retrieves available transactions.",
                "consumes": [
                    "application/json"
                ],
                "produces": [
                    "application/json"
                ],
                "tags": [
                    "transaction"
                ],
                "summary": "Get transaction",
                "parameters": [
                    {
                        "type": "integer",
                        "default": 1,
                        "description": "Page",
                        "name": "page",
                        "in": "query"
                    },
                    {
                        "type": "integer",
                        "default": 10,
                        "description": "Per Page",
                        "name": "per_page",
                        "in": "query"
                    }
                ],
                "responses": {
                    "200": {
                        "description": "Successful transaction list response",
                        "schema": {
                            "allOf": [
                                {
                                    "$ref": "#/definitions/model.BaseResponse"
                                },
                                {
                                    "type": "object",
                                    "properties": {
                                        "data": {
                                            "type": "array",
                                            "items": {
                                                "$ref": "#/definitions/model.TransactionResponse"
                                            }
                                        }
                                    }
                                }
                            ]
                        }
                    },
                    "401": {
                        "description": "Unauthorized error response",
                        "schema": {
                            "$ref": "#/definitions/model.BaseResponse"
                        }
                    }
                }
            },
            "post": {
                "security": [
                    {
                        "AccessToken": []
                    }
                ],
                "description": "Creates a new transaction.",
                "consumes": [
                    "application/json"
                ],
                "produces": [
                    "application/json"
                ],
                "tags": [
                    "transaction"
                ],
                "summary": "Create transaction",
                "parameters": [
                    {
                        "description": "Create Transaction Request",
                        "name": "request",
                        "in": "body",
                        "required": true,
                        "schema": {
                            "$ref": "#/definitions/model.CreateTransactionRequest"
                        }
                    }
                ],
                "responses": {
                    "201": {
                        "description": "Successful transaction creation response",
                        "schema": {
                            "$ref": "#/definitions/model.BaseResponse"
                        }
                    },
                    "400": {
                        "description": "Bad request error response",
                        "schema": {
                            "$ref": "#/definitions/model.BaseResponse"
                        }
                    },
                    "401": {
                        "description": "Unauthorized error response",
                        "schema": {
                            "$ref": "#/definitions/model.BaseResponse"
                        }
                    },
                    "422": {
                        "description": "Validation error response",
                        "schema": {
                            "$ref": "#/definitions/model.BaseResponse"
                        }
                    }
                }
            }
        }
    },
    "definitions": {
        "model.AuthMe": {
            "type": "object",
            "properties": {
                "email": {
                    "type": "string"
                },
                "id": {
                    "type": "integer"
                },
                "name": {
                    "type": "string"
                }
            }
        },
        "model.BaseResponse": {
            "type": "object",
            "properties": {
                "data": {},
                "message": {
                    "type": "string",
                    "example": "Message!"
                }
            }
        },
        "model.CreateLoanRequest": {
            "type": "object",
            "required": [
                "assets_name",
                "otr",
                "tenor_months"
            ],
            "properties": {
                "assets_name": {
                    "type": "string",
                    "example": "Credit Motorcycle"
                },
                "otr": {
                    "type": "number",
                    "minimum": 0,
                    "example": 15000000
                },
                "tenor_months": {
                    "type": "integer",
                    "maximum": 32,
                    "minimum": 1,
                    "example": 18
                }
            }
        },
        "model.CreateTransactionRequest": {
            "type": "object",
            "required": [
                "amount",
                "loan_id"
            ],
            "properties": {
                "amount": {
                    "type": "number",
                    "minimum": 0,
                    "example": 1000
                },
                "loan_id": {
                    "type": "integer",
                    "example": 1
                }
            }
        },
        "model.CustomerResponse": {
            "type": "object",
            "properties": {
                "date_birth": {
                    "type": "string"
                },
                "email": {
                    "type": "string"
                },
                "full_name": {
                    "type": "string"
                },
                "id": {
                    "type": "integer"
                },
                "identity_file": {
                    "type": "string"
                },
                "legal_name": {
                    "type": "string"
                },
                "nik": {
                    "type": "string"
                },
                "place_birth": {
                    "type": "string"
                },
                "salary": {
                    "type": "number"
                },
                "selfie_file": {
                    "type": "string"
                }
            }
        },
        "model.LoanResponse": {
            "type": "object",
            "properties": {
                "admin_fee": {
                    "type": "number"
                },
                "assets_name": {
                    "type": "string"
                },
                "end_date": {
                    "type": "string"
                },
                "id": {
                    "type": "integer"
                },
                "installment_amount": {
                    "type": "number"
                },
                "otr": {
                    "type": "number"
                },
                "start_date": {
                    "type": "string"
                },
                "tenor_months": {
                    "type": "integer"
                },
                "total_amount": {
                    "type": "number"
                },
                "total_paid": {
                    "type": "integer"
                }
            }
        },
        "model.LoginRequest": {
            "type": "object",
            "required": [
                "email",
                "password"
            ],
            "properties": {
                "email": {
                    "type": "string"
                },
                "password": {
                    "type": "string"
                }
            }
        },
        "model.TenorResponse": {
            "type": "object",
            "properties": {
                "amount": {
                    "type": "number"
                },
                "id": {
                    "type": "integer"
                },
                "month": {
                    "type": "integer"
                }
            }
        },
        "model.TransactionResponse": {
            "type": "object",
            "properties": {
                "amount": {
                    "type": "number"
                },
                "id": {
                    "type": "integer"
                },
                "interest_amount": {
                    "type": "number"
                },
                "loan_id": {
                    "type": "integer"
                }
            }
        }
    },
    "securityDefinitions": {
        "AccessToken": {
            "type": "apiKey",
            "name": "Authorization",
            "in": "header"
        }
    }
}